<?xml version="1.0" encoding="UTF-8" standalone="no"?><entities>
	<entity>
		<entity-name>gr.scriptum.domain.TaskState</entity-name>
		<entity-width>120</entity-width>
		<entity-height>30</entity-height>
		<entity-X-Coordinate>251</entity-X-Coordinate>
		<entity-Y-Coordinate>2980</entity-Y-Coordinate>
		<primary-collapsed>false</primary-collapsed>
		<relation-collapsed>false</relation-collapsed>
		<basic-collapsed>false</basic-collapsed>
	</entity>

	<entity>
		<entity-name>gr.scriptum.domain.ProtocolDependency</entity-name>
		<entity-width>208</entity-width>
		<entity-height>30</entity-height>
		<entity-X-Coordinate>983</entity-X-Coordinate>
		<entity-Y-Coordinate>2205</entity-Y-Coordinate>
		<primary-collapsed>false</primary-collapsed>
		<relation-collapsed>false</relation-collapsed>
		<basic-collapsed>false</basic-collapsed>
	</entity>

	<entity>
		<entity-name>gr.scriptum.domain.DocumentType</entity-name>
		<entity-width>120</entity-width>
		<entity-height>406</entity-height>
		<entity-X-Coordinate>405</entity-X-Coordinate>
		<entity-Y-Coordinate>1750</entity-Y-Coordinate>
		<primary-collapsed>false</primary-collapsed>
		<relation-collapsed>false</relation-collapsed>
		<basic-collapsed>false</basic-collapsed>
	</entity>

	<entity>
		<entity-name>gr.scriptum.domain.Subject</entity-name>
		<entity-width>120</entity-width>
		<entity-height>30</entity-height>
		<entity-X-Coordinate>50</entity-X-Coordinate>
		<entity-Y-Coordinate>2576</entity-Y-Coordinate>
		<primary-collapsed>false</primary-collapsed>
		<relation-collapsed>false</relation-collapsed>
		<basic-collapsed>false</basic-collapsed>
	</entity>

	<entity>
		<entity-name>gr.scriptum.domain.ApplicationParameter</entity-name>
		<entity-width>120</entity-width>
		<entity-height>30</entity-height>
		<entity-X-Coordinate>490</entity-X-Coordinate>
		<entity-Y-Coordinate>50</entity-Y-Coordinate>
		<primary-collapsed>false</primary-collapsed>
		<relation-collapsed>false</relation-collapsed>
		<basic-collapsed>false</basic-collapsed>
	</entity>

	<entity>
		<entity-name>gr.scriptum.domain.ProjectUser</entity-name>
		<entity-width>120</entity-width>
		<entity-height>30</entity-height>
		<entity-X-Coordinate>839</entity-X-Coordinate>
		<entity-Y-Coordinate>1600</entity-Y-Coordinate>
		<primary-collapsed>false</primary-collapsed>
		<relation-collapsed>false</relation-collapsed>
		<basic-collapsed>false</basic-collapsed>
	</entity>

	<entity>
		<entity-name>gr.scriptum.domain.Department</entity-name>
		<entity-width>182</entity-width>
		<entity-height>30</entity-height>
		<entity-X-Coordinate>609</entity-X-Coordinate>
		<entity-Y-Coordinate>1396</entity-Y-Coordinate>
		<primary-collapsed>false</primary-collapsed>
		<relation-collapsed>false</relation-collapsed>
		<basic-collapsed>false</basic-collapsed>
	</entity>

	<entity>
		<entity-name>gr.scriptum.domain.Resource</entity-name>
		<entity-width>207</entity-width>
		<entity-height>30</entity-height>
		<entity-X-Coordinate>988</entity-X-Coordinate>
		<entity-Y-Coordinate>2896</entity-Y-Coordinate>
		<primary-collapsed>false</primary-collapsed>
		<relation-collapsed>false</relation-collapsed>
		<basic-collapsed>false</basic-collapsed>
	</entity>

	<entity>
		<entity-name>gr.scriptum.domain.Permission</entity-name>
		<entity-width>120</entity-width>
		<entity-height>30</entity-height>
		<entity-X-Coordinate>956</entity-X-Coordinate>
		<entity-Y-Coordinate>2690</entity-Y-Coordinate>
		<primary-collapsed>false</primary-collapsed>
		<relation-collapsed>false</relation-collapsed>
		<basic-collapsed>false</basic-collapsed>
	</entity>

	<entity>
		<entity-name>gr.scriptum.domain.Company</entity-name>
		<entity-width>120</entity-width>
		<entity-height>30</entity-height>
		<entity-X-Coordinate>747</entity-X-Coordinate>
		<entity-Y-Coordinate>900</entity-Y-Coordinate>
		<primary-collapsed>false</primary-collapsed>
		<relation-collapsed>false</relation-collapsed>
		<basic-collapsed>false</basic-collapsed>
	</entity>

	<entity>
		<entity-name>gr.scriptum.domain.Contact</entity-name>
		<entity-width>120</entity-width>
		<entity-height>30</entity-height>
		<entity-X-Coordinate>492</entity-X-Coordinate>
		<entity-Y-Coordinate>2390</entity-Y-Coordinate>
		<primary-collapsed>false</primary-collapsed>
		<relation-collapsed>false</relation-collapsed>
		<basic-collapsed>false</basic-collapsed>
	</entity>

	<entity>
		<entity-name>gr.scriptum.domain.CompanyType</entity-name>
		<entity-width>120</entity-width>
		<entity-height>30</entity-height>
		<entity-X-Coordinate>710</entity-X-Coordinate>
		<entity-Y-Coordinate>100</entity-Y-Coordinate>
		<primary-collapsed>false</primary-collapsed>
		<relation-collapsed>false</relation-collapsed>
		<basic-collapsed>false</basic-collapsed>
	</entity>

	<entity>
		<entity-name>gr.scriptum.domain.Users</entity-name>
		<entity-width>120</entity-width>
		<entity-height>30</entity-height>
		<entity-X-Coordinate>770</entity-X-Coordinate>
		<entity-Y-Coordinate>2862</entity-Y-Coordinate>
		<primary-collapsed>false</primary-collapsed>
		<relation-collapsed>false</relation-collapsed>
		<basic-collapsed>false</basic-collapsed>
	</entity>

	<entity>
		<entity-name>gr.scriptum.domain.DiavgeiaDecisionType</entity-name>
		<entity-width>120</entity-width>
		<entity-height>30</entity-height>
		<entity-X-Coordinate>50</entity-X-Coordinate>
		<entity-Y-Coordinate>476</entity-Y-Coordinate>
		<primary-collapsed>false</primary-collapsed>
		<relation-collapsed>false</relation-collapsed>
		<basic-collapsed>false</basic-collapsed>
	</entity>

	<entity>
		<entity-name>gr.scriptum.domain.ApplicationLog</entity-name>
		<entity-width>120</entity-width>
		<entity-height>30</entity-height>
		<entity-X-Coordinate>50</entity-X-Coordinate>
		<entity-Y-Coordinate>50</entity-Y-Coordinate>
		<primary-collapsed>false</primary-collapsed>
		<relation-collapsed>false</relation-collapsed>
		<basic-collapsed>false</basic-collapsed>
	</entity>

	<entity>
		<entity-name>gr.scriptum.domain.TaskMessage</entity-name>
		<entity-width>120</entity-width>
		<entity-height>30</entity-height>
		<entity-X-Coordinate>383</entity-X-Coordinate>
		<entity-Y-Coordinate>2737</entity-Y-Coordinate>
		<primary-collapsed>false</primary-collapsed>
		<relation-collapsed>false</relation-collapsed>
		<basic-collapsed>false</basic-collapsed>
	</entity>

	<entity>
		<entity-name>gr.scriptum.domain.DistributionMethod</entity-name>
		<entity-width>120</entity-width>
		<entity-height>30</entity-height>
		<entity-X-Coordinate>1012</entity-X-Coordinate>
		<entity-Y-Coordinate>1636</entity-Y-Coordinate>
		<primary-collapsed>false</primary-collapsed>
		<relation-collapsed>false</relation-collapsed>
		<basic-collapsed>false</basic-collapsed>
	</entity>

	<entity>
		<entity-name>gr.scriptum.domain.ProtocolCorrespondent</entity-name>
		<entity-width>272</entity-width>
		<entity-height>566</entity-height>
		<entity-X-Coordinate>1144</entity-X-Coordinate>
		<entity-Y-Coordinate>1843</entity-Y-Coordinate>
		<primary-collapsed>false</primary-collapsed>
		<relation-collapsed>false</relation-collapsed>
		<basic-collapsed>false</basic-collapsed>
	</entity>

	<entity>
		<entity-name>gr.scriptum.domain.ProjectTask</entity-name>
		<entity-width>120</entity-width>
		<entity-height>30</entity-height>
		<entity-X-Coordinate>270</entity-X-Coordinate>
		<entity-Y-Coordinate>1378</entity-Y-Coordinate>
		<primary-collapsed>false</primary-collapsed>
		<relation-collapsed>false</relation-collapsed>
		<basic-collapsed>false</basic-collapsed>
	</entity>

	<entity>
		<entity-name>gr.scriptum.domain.CorrespondentGroup</entity-name>
		<entity-width>120</entity-width>
		<entity-height>306</entity-height>
		<entity-X-Coordinate>1370</entity-X-Coordinate>
		<entity-Y-Coordinate>1510</entity-Y-Coordinate>
		<primary-collapsed>false</primary-collapsed>
		<relation-collapsed>false</relation-collapsed>
		<basic-collapsed>false</basic-collapsed>
	</entity>

	<entity>
		<entity-name>gr.scriptum.domain.Role</entity-name>
		<entity-width>120</entity-width>
		<entity-height>30</entity-height>
		<entity-X-Coordinate>672</entity-X-Coordinate>
		<entity-Y-Coordinate>2481</entity-Y-Coordinate>
		<primary-collapsed>false</primary-collapsed>
		<relation-collapsed>false</relation-collapsed>
		<basic-collapsed>false</basic-collapsed>
	</entity>

	<entity>
		<entity-name>gr.scriptum.domain.DiavgeiaSubjectGroup</entity-name>
		<entity-width>120</entity-width>
		<entity-height>30</entity-height>
		<entity-X-Coordinate>50</entity-X-Coordinate>
		<entity-Y-Coordinate>744</entity-Y-Coordinate>
		<primary-collapsed>false</primary-collapsed>
		<relation-collapsed>false</relation-collapsed>
		<basic-collapsed>false</basic-collapsed>
	</entity>

	<entity>
		<entity-name>gr.scriptum.domain.Parameter</entity-name>
		<entity-width>120</entity-width>
		<entity-height>30</entity-height>
		<entity-X-Coordinate>710</entity-X-Coordinate>
		<entity-Y-Coordinate>1178</entity-Y-Coordinate>
		<primary-collapsed>false</primary-collapsed>
		<relation-collapsed>false</relation-collapsed>
		<basic-collapsed>false</basic-collapsed>
	</entity>

	<entity>
		<entity-name>gr.scriptum.domain.ProtocolDocument</entity-name>
		<entity-width>240</entity-width>
		<entity-height>30</entity-height>
		<entity-X-Coordinate>710</entity-X-Coordinate>
		<entity-Y-Coordinate>1869</entity-Y-Coordinate>
		<primary-collapsed>false</primary-collapsed>
		<relation-collapsed>false</relation-collapsed>
		<basic-collapsed>false</basic-collapsed>
	</entity>

	<entity>
		<entity-name>gr.scriptum.domain.ProtocolNumber</entity-name>
		<entity-width>120</entity-width>
		<entity-height>30</entity-height>
		<entity-X-Coordinate>270</entity-X-Coordinate>
		<entity-Y-Coordinate>2124</entity-Y-Coordinate>
		<primary-collapsed>false</primary-collapsed>
		<relation-collapsed>false</relation-collapsed>
		<basic-collapsed>false</basic-collapsed>
	</entity>

	<entity>
		<entity-name>gr.scriptum.domain.TaskDocument</entity-name>
		<entity-width>120</entity-width>
		<entity-height>30</entity-height>
		<entity-X-Coordinate>336</entity-X-Coordinate>
		<entity-Y-Coordinate>2560</entity-Y-Coordinate>
		<primary-collapsed>false</primary-collapsed>
		<relation-collapsed>false</relation-collapsed>
		<basic-collapsed>false</basic-collapsed>
	</entity>

	<entity>
		<entity-name>gr.scriptum.domain.ProjectUserId</entity-name>
		<entity-width>120</entity-width>
		<entity-height>30</entity-height>
		<entity-X-Coordinate>490</entity-X-Coordinate>
		<entity-Y-Coordinate>1600</entity-Y-Coordinate>
		<primary-collapsed>false</primary-collapsed>
		<relation-collapsed>false</relation-collapsed>
		<basic-collapsed>false</basic-collapsed>
	</entity>

	<entity>
		<entity-name>gr.scriptum.domain.UserAssignment</entity-name>
		<entity-width>120</entity-width>
		<entity-height>30</entity-height>
		<entity-X-Coordinate>1016</entity-X-Coordinate>
		<entity-Y-Coordinate>2790</entity-Y-Coordinate>
		<primary-collapsed>false</primary-collapsed>
		<relation-collapsed>false</relation-collapsed>
		<basic-collapsed>false</basic-collapsed>
	</entity>

	<entity>
		<entity-name>gr.scriptum.domain.UserHierarchy</entity-name>
		<entity-width>120</entity-width>
		<entity-height>30</entity-height>
		<entity-X-Coordinate>590</entity-X-Coordinate>
		<entity-Y-Coordinate>2891</entity-Y-Coordinate>
		<primary-collapsed>false</primary-collapsed>
		<relation-collapsed>false</relation-collapsed>
		<basic-collapsed>false</basic-collapsed>
	</entity>

	<entity>
		<entity-name>gr.scriptum.domain.ProtocolBook</entity-name>
		<entity-width>120</entity-width>
		<entity-height>406</entity-height>
		<entity-X-Coordinate>91</entity-X-Coordinate>
		<entity-Y-Coordinate>1742</entity-Y-Coordinate>
		<primary-collapsed>false</primary-collapsed>
		<relation-collapsed>false</relation-collapsed>
		<basic-collapsed>false</basic-collapsed>
	</entity>

	<entity>
		<entity-name>gr.scriptum.domain.TaskPriority</entity-name>
		<entity-width>120</entity-width>
		<entity-height>30</entity-height>
		<entity-X-Coordinate>50</entity-X-Coordinate>
		<entity-Y-Coordinate>2804</entity-Y-Coordinate>
		<primary-collapsed>false</primary-collapsed>
		<relation-collapsed>false</relation-collapsed>
		<basic-collapsed>false</basic-collapsed>
	</entity>

	<entity>
		<entity-name>gr.scriptum.domain.ProtocolRelation</entity-name>
		<entity-width>120</entity-width>
		<entity-height>30</entity-height>
		<entity-X-Coordinate>50</entity-X-Coordinate>
		<entity-Y-Coordinate>2290</entity-Y-Coordinate>
		<primary-collapsed>false</primary-collapsed>
		<relation-collapsed>false</relation-collapsed>
		<basic-collapsed>false</basic-collapsed>
	</entity>

	<entity>
		<entity-name>gr.scriptum.domain.TaskType</entity-name>
		<entity-width>120</entity-width>
		<entity-height>30</entity-height>
		<entity-X-Coordinate>690</entity-X-Coordinate>
		<entity-Y-Coordinate>2380</entity-Y-Coordinate>
		<primary-collapsed>false</primary-collapsed>
		<relation-collapsed>false</relation-collapsed>
		<basic-collapsed>false</basic-collapsed>
	</entity>

	<entity>
		<entity-name>gr.scriptum.domain.TaskResult</entity-name>
		<entity-width>120</entity-width>
		<entity-height>30</entity-height>
		<entity-X-Coordinate>270</entity-X-Coordinate>
		<entity-Y-Coordinate>2896</entity-Y-Coordinate>
		<primary-collapsed>false</primary-collapsed>
		<relation-collapsed>false</relation-collapsed>
		<basic-collapsed>false</basic-collapsed>
	</entity>

	<entity>
		<entity-name>gr.scriptum.domain.Dossier</entity-name>
		<entity-width>120</entity-width>
		<entity-height>30</entity-height>
		<entity-X-Coordinate>50</entity-X-Coordinate>
		<entity-Y-Coordinate>992</entity-Y-Coordinate>
		<primary-collapsed>false</primary-collapsed>
		<relation-collapsed>false</relation-collapsed>
		<basic-collapsed>false</basic-collapsed>
	</entity>

	<entity>
		<entity-name>gr.scriptum.domain.Protocol</entity-name>
		<entity-width>230</entity-width>
		<entity-height>301</entity-height>
		<entity-X-Coordinate>951</entity-X-Coordinate>
		<entity-Y-Coordinate>2385</entity-Y-Coordinate>
		<primary-collapsed>false</primary-collapsed>
		<relation-collapsed>false</relation-collapsed>
		<basic-collapsed>true</basic-collapsed>
	</entity>

	<entity>
		<entity-name>gr.scriptum.domain.Project</entity-name>
		<entity-width>120</entity-width>
		<entity-height>30</entity-height>
		<entity-X-Coordinate>50</entity-X-Coordinate>
		<entity-Y-Coordinate>1378</entity-Y-Coordinate>
		<primary-collapsed>false</primary-collapsed>
		<relation-collapsed>false</relation-collapsed>
		<basic-collapsed>false</basic-collapsed>
	</entity>
</entities>